
[
  {
    "id": 1,
    "question": "पानी का रासायनिक सूत्र क्या है?",
    "options": ["CO₂", "H₂O", "O₂", "NaCl"],
    "answer": 1,
    "reason": "पानी दो हाइड्रोजन (H) और एक ऑक्सीजन (O) परमाणु से मिलकर बनता है, इसलिए इसका रासायनिक सूत्र H₂O है।"
  },
  {
    "id": 2,
    "question": "मनुष्य के शरीर का सबसे बड़ा अंग कौन-सा है?",
    "options": ["हृदय", "यकृत", "त्वचा", "फेफड़ा"],
    "answer": 2,
    "reason": "त्वचा मानव शरीर का सबसे बड़ा अंग है। यह शरीर को बाहरी संक्रमण, धूप और चोट से बचाती है।"
  },
  {
    "id": 3,
    "question": "पौधे भोजन बनाने के लिए किस गैस का उपयोग करते हैं?",
    "options": ["ऑक्सीजन", "कार्बन डाइऑक्साइड", "नाइट्रोजन", "हाइड्रोजन"],
    "answer": 1,
    "reason": "प्रकाश संश्लेषण के दौरान पौधे कार्बन डाइऑक्साइड लेकर अपना भोजन बनाते हैं और ऑक्सीजन छोड़ते हैं।"
  },
  {
    "id": 4,
    "question": "सूर्य किस प्रकार का तारा है?",
    "options": ["लाल दानव", "सफेद बौना", "पीला बौना", "न्यूट्रॉन तारा"],
    "answer": 2,
    "reason": "सूर्य G-प्रकार का मुख्य अनुक्रम तारा है, जिसे सामान्य भाषा में पीला बौना (Yellow Dwarf) कहा जाता है।"
  },
  {
    "id": 5,
    "question": "मानव शरीर में रक्त को पंप करने वाला अंग कौन-सा है?",
    "options": ["मस्तिष्क", "फेफड़ा", "हृदय", "यकृत"],
    "answer": 2,
    "reason": "हृदय लगातार संकुचन और प्रसार करके पूरे शरीर में रक्त का संचार करता है।"
  },

{
  "id": 6,
  "question": "मानव शरीर में कुल कितनी हड्डियाँ होती हैं?",
  "options": ["196", "206", "216", "226"],
  "answer": 1,
  "reason": "एक वयस्क मनुष्य के शरीर में सामान्यतः 206 हड्डियाँ होती हैं।"
},
{
  "id": 7,
  "question": "सौरमंडल का सबसे बड़ा ग्रह कौन-सा है?",
  "options": ["पृथ्वी", "मंगल", "बृहस्पति", "शनि"],
  "answer": 2,
  "reason": "बृहस्पति सौरमंडल का सबसे बड़ा ग्रह है और इसका द्रव्यमान सभी ग्रहों में सबसे अधिक है।"
},
{
  "id": 8,
  "question": "पृथ्वी का प्राकृतिक उपग्रह कौन है?",
  "options": ["सूर्य", "चंद्रमा", "मंगल", "शुक्र"],
  "answer": 1,
  "reason": "चंद्रमा पृथ्वी का एकमात्र प्राकृतिक उपग्रह है।"
},
{
  "id": 9,
  "question": "श्वसन के लिए मनुष्य कौन-सी गैस लेता है?",
  "options": ["कार्बन डाइऑक्साइड", "हाइड्रोजन", "ऑक्सीजन", "नाइट्रोजन"],
  "answer": 2,
  "reason": "मनुष्य श्वसन के लिए ऑक्सीजन ग्रहण करता है और कार्बन डाइऑक्साइड बाहर छोड़ता है।"
},
{
  "id": 10,
  "question": "पौधों का हरा रंग किस वर्णक के कारण होता है?",
  "options": ["हीमोग्लोबिन", "क्लोरोफिल", "मेलानिन", "कैरोटीन"],
  "answer": 1,
  "reason": "क्लोरोफिल पौधों को हरा रंग देता है और प्रकाश संश्लेषण में मुख्य भूमिका निभाता है।"
}
]
